fastdeploy_cli/__init__.py
fastdeploy_cli/mycli.py
fastdeploy_cli-0.1.2.dist-info/METADATA
fastdeploy_cli-0.1.2.dist-info/WHEEL
fastdeploy_cli-0.1.2.dist-info/entry_points.txt
fastdeploy_cli-0.1.2.dist-info/top_level.txt
fastdeploy_cli-0.1.2.dist-info/RECORD
