Metadata-Version: 2.4
Name: fastdeploy_cli
Version: 0.1.2
Summary: CLI tool to simplify web app deployments using Docker & Nixpacks
Author-email: "Olayinka Jimba Jr." <ojimba01@gmail.com>
Project-URL: Homepage, https://github.com/ojimba01/fast-deploy
Project-URL: Repository, https://github.com/ojimba01/fast-deploy
Project-URL: Bug Tracker, https://github.com/ojimba01/fast-deploy/issues
Keywords: deployment,docker,nixpacks,aws,cli
Classifier: Programming Language :: Python :: 3
Classifier: License :: OSI Approved :: MIT License
Classifier: Operating System :: OS Independent
Requires-Python: >=3.9
Requires-Dist: click
Requires-Dist: docker
Requires-Dist: requests
